connmonitor/__init__.py
connmonitor/connmonitor.py
connmonitor-4.1.3.data/data/lib/systemd/system/connmonitor.service
connmonitor-4.1.3.dist-info/METADATA
connmonitor-4.1.3.dist-info/RECORD
connmonitor-4.1.3.dist-info/WHEEL
connmonitor-4.1.3.dist-info/entry_points.txt
connmonitor-4.1.3.dist-info/top_level.txt
